zipvoice/__init__.py
zipvoice-0.1.0.dist-info/LICENSE
zipvoice-0.1.0.dist-info/METADATA
zipvoice-0.1.0.dist-info/WHEEL
zipvoice-0.1.0.dist-info/top_level.txt
zipvoice-0.1.0.dist-info/RECORD
